{
    "relationships": [
        {
            "relationshipId": 1,
            "relationshipName": "user",
            "otherEntityName": "user",
            "relationshipType": "many-to-one",
            "otherEntityField": "id"
        },
        {
            "relationshipId": 2,
            "relationshipType": "one-to-one",
            "relationshipName": "productAddress",
            "otherEntityName": "productAddress",
            "otherEntityField": "id",
            "ownerSide": true,
            "otherEntityRelationshipName": "product"
        },
        {
            "relationshipId": 3,
            "relationshipType": "one-to-many",
            "relationshipName": "comment",
            "otherEntityName": "comment",
            "otherEntityRelationshipName": "product"
        },
        {
            "relationshipName": "category",
            "otherEntityName": "category",
            "relationshipType": "many-to-many",
            "otherEntityField": "title",
            "ownerSide": true
        },
        {
            "relationshipName": "tag",
            "otherEntityName": "tag",
            "relationshipType": "many-to-many",
            "otherEntityField": "name",
            "ownerSide": true
        }
    ],
    "fields": [
        {
            "fieldId": 1,
            "fieldName": "title",
            "fieldType": "String"
        },
        {
            "fieldId": 2,
            "fieldName": "image",
            "fieldType": "String"
        },
        {
            "fieldId": 3,
            "fieldName": "latitude",
            "fieldType": "String"
        },
        {
            "fieldId": 4,
            "fieldName": "longitude",
            "fieldType": "String"
        }
    ],
    "changelogDate": "20160723003456",
    "dto": "no",
    "service": "no",
    "entityTableName": "product",
    "pagination": "no"
}
